ProxVNC/__init__.py
ProxVNC/config.py
ProxVNC/core/ProxmoxVNC.py
ProxVNC/core/__init__.py
ProxVNC/core/connection.py
ProxVNC/core/terminal.py
ProxVNC/core/utils.py
ProxVNC/proxmoxer/__init__.py
ProxVNC/proxmoxer/core.py
ProxVNC/proxmoxer/backends/__init__.py
ProxVNC/proxmoxer/backends/command_base.py
ProxVNC/proxmoxer/backends/https.py
ProxVNC/proxmoxer/backends/local.py
ProxVNC/proxmoxer/backends/openssh.py
ProxVNC/proxmoxer/backends/ssh_paramiko.py
ProxVNC/proxmoxer/tools/__init__.py
ProxVNC/proxmoxer/tools/files.py
ProxVNC/proxmoxer/tools/tasks.py
proxvnc-1.2.1.dist-info/licenses/LICENSE
proxvnc-1.2.1.dist-info/METADATA
proxvnc-1.2.1.dist-info/WHEEL
proxvnc-1.2.1.dist-info/top_level.txt
proxvnc-1.2.1.dist-info/RECORD
