Metadata-Version: 2.4
Name: ProxVNC
Version: 1.2.1
Summary: A python package that allows connecting and sending commands direcly to a proxmox node/lxc via vnc websocket.
Author: Xavier Giralt
License: MIT License
Project-URL: Homepage, https://github.com/xgiralt64/ProxVNC
Project-URL: Repository, https://github.com/xgiralt64/ProxVNC
Keywords: package,proxmox,vnc,websocket
Requires-Python: >=3.8
License-File: LICENSE
Requires-Dist: requests>=2.32.0
Requires-Dist: websocket-client>=1.9.0
Requires-Dist: urllib3>=2.5.0
Dynamic: license-file
